[
  {
    "id": 1,
    "name": "Tech Haven",
    "image": "https://picsum.photos/id/201/300/200",
    "description": "Your ultimate destination for gadgets and electronics.",
    "contact": "contact@techhaven.com",
    "location": "123 Main Street, Cityville",
    "featured": true,
    "products": [
      { "name": "Smartphone X", "image": "https://picsum.photos/id/301/200/150", "cta": "#" },
      { "name": "Wireless Headphones", "image": "https://picsum.photos/id/302/200/150", "cta": "#" },
      { "name": "Gaming Laptop", "image": "https://picsum.photos/id/303/200/150", "cta": "#" }
    ]
  },
  {
    "id": 2,
    "name": "Fashion Boutique",
    "image": "https://picsum.photos/id/202/300/200",
    "description": "Trendy clothing and accessories for modern fashion lovers.",
    "contact": "hello@fashionboutique.com",
    "location": "456 Market Street, Cityville",
    "featured": true,
    "products": [
      { "name": "Summer Dress", "image": "https://picsum.photos/id/304/200/150", "cta": "#" },
      { "name": "Leather Handbag", "image": "https://picsum.photos/id/305/200/150", "cta": "#" },
      { "name": "Sunglasses", "image": "https://picsum.photos/id/306/200/150", "cta": "#" }
    ]
  },
  {
    "id": 3,
    "name": "Gourmet Delights",
    "image": "https://picsum.photos/id/203/300/200",
    "description": "Premium gourmet food items and delicacies.",
    "contact": "info@gourmetdelights.com",
    "location": "789 Food Lane, Cityville",
    "featured": false,
    "products": [
      { "name": "Artisan Cheese", "image": "https://picsum.photos/id/307/200/150", "cta": "#" },
      { "name": "Chocolate Box", "image": "https://picsum.photos/id/308/200/150", "cta": "#" },
      { "name": "Organic Olive Oil", "image": "https://picsum.photos/id/309/200/150", "cta": "#" }
    ]
  }
]
